Metadata-Version: 2.1
Name: soda-core-spark
Version: 3.5.6
License-File: LICENSE
Requires-Dist: soda-core==3.5.6
Provides-Extra: databricks
Requires-Dist: databricks-sql-connector; extra == "databricks"
Provides-Extra: hive
Requires-Dist: PyHive[hive]; extra == "hive"
Provides-Extra: odbc
Requires-Dist: pyodbc; extra == "odbc"
